overfast_api/Gamemodes.py
overfast_api/Heroes.py
overfast_api/Maps.py
overfast_api/Players.py
overfast_api/RestAdapter.py
overfast_api/__init__.py
overfast_api/exceptions.py
overfast_api/models.py
overfast_api-1.0.0.dist-info/LICENSE
overfast_api-1.0.0.dist-info/METADATA
overfast_api-1.0.0.dist-info/WHEEL
overfast_api-1.0.0.dist-info/top_level.txt
overfast_api-1.0.0.dist-info/RECORD
